roe/__init__.py
roe/api/__init__.py
roe/api/agents.py
roe/auth.py
roe/client.py
roe/config.py
roe/exceptions.py
roe/models/__init__.py
roe/models/agent.py
roe/models/file.py
roe/models/job.py
roe/models/responses.py
roe/models/user.py
roe/utils/__init__.py
roe/utils/file_detection.py
roe/utils/http_client.py
roe/utils/pagination.py
roe_ai-0.2.0.dist-info/WHEEL
roe_ai-0.2.0.dist-info/METADATA
roe_ai-0.2.0.dist-info/RECORD
