Metadata-Version: 2.4
Name: roe-ai
Version: 0.2.0
Summary: Python SDK for the Roe AI API
Author: Roe AI
Author-email: Roe AI <founders@roe-ai.com>
License-Expression: Apache-2.0
Requires-Dist: httpx>=0.28.1
Requires-Dist: pydantic>=2.11.7
Requires-Python: >=3.10
Project-URL: Homepage, https://github.com/roe-ai/roe-python
Project-URL: Repository, https://github.com/roe-ai/roe-python
